{"id":104196,"name":"ニセコイ OAD","name_cn":"伪恋 OAD","type":"动画","image":"2d/bb/104196_mIzDE.jpg","link":"https://bgm.tv/subject/104196","eps":4,"collection":{"on_hold":80,"dropped":36,"wish":386,"collect":3215,"doing":92},"date":"2014-10-03","summary":"漫画单行本第14卷推出同捆OVA的限定版（完全预约生产），时长约25分钟，改编自原作漫画第58话《丢失》和第64话《巫女小姐》。\r\n\r\n漫画单行本第16卷预定于2015年2月4日发售，并将推出同捆OVA的限定版（预约生产），时长约25分钟，改编自原作漫画第65话《酒后吐真言》和第71话《兼职》。\r\n\r\n漫画单行本第17卷将于2015年4月3日发售，限定版同捆OAD，动画内容改编自原作第81话“澡堂”。\r\n\r\n漫画单行本第21卷将于2016年1月4日发售，限定版同捆OAD。","rating":{"rank":2830,"total":1772,"count":{"1":3,"2":2,"3":9,"4":15,"5":91,"6":398,"7":831,"8":355,"9":30,"10":38},"score":6.9},"updated_at":"2023-10-12T19:11:56+08:00"}